conector_total/__init__.py
conector_total/__main__.py
conector_total/names.txt
conector_total/speaker.py
conector_total/speakers/__init__.py
conector_total/speakers/agustin.py
conector_total-0.3.0.dist-info/licenses/LICENSE.txt
conector_total-0.3.0.dist-info/METADATA
conector_total-0.3.0.dist-info/WHEEL
conector_total-0.3.0.dist-info/entry_points.txt
conector_total-0.3.0.dist-info/top_level.txt
conector_total-0.3.0.dist-info/RECORD
