Metadata-Version: 2.4
Name: conector_total
Version: 0.3.0
Summary: My first package!
Author-email: agustin <agustincepeda1@gmail.com>
Maintainer-email: agustin <agustincepeda1@gmail.com>
License: Copyright 2025 agustin
Project-URL: Homepage, https://github.com/jfuruness/justin_furuness
Project-URL: Documentation, https://github.com/jfuruness/justin_furuness/README.md
Keywords: agustin
Classifier: Programming Language :: Python :: 3.9
Classifier: Programming Language :: Python :: Implementation :: CPython
Classifier: License :: OSI Approved :: BSD License
Classifier: Intended Audience :: Developers
Classifier: Operating System :: POSIX :: Linux
Classifier: Operating System :: Microsoft :: Windows
Classifier: Operating System :: MacOS
Classifier: Operating System :: MacOS :: MacOS X
Requires-Python: >=3.9
License-File: LICENSE.txt
Requires-Dist: colorama~=0.0
Provides-Extra: test
Requires-Dist: twine; extra == "test"
Requires-Dist: build; extra == "test"
Dynamic: license-file
